GravityLab-10.0.0.dist-info/RECORD
GravityLab-10.0.0.dist-info/METADATA
GravityLab-10.0.0.dist-info/LICENSE
GravityLab-10.0.0.dist-info/WHEEL
GravityLab-10.0.0.dist-info/top_level.txt
gravitylab/solvers.cpython-37m-x86_64-linux-gnu.so
gravitylab/simulate.py
gravitylab/__init__.py
gravitylab/example.py
