Metadata-Version: 2.1
Name: GravityLab
Version: 10.0.0
Summary: Fast astrophysical N-body simulator
Home-page: https://github.com/Kushaalkumar-pothula/gravitylab
Author: Kushaal Kumar Pothula
Author-email: kushaalkumar.astronomer@gmail.com
License: MIT
Platform: UNKNOWN
License-File: LICENSE
Requires-Dist: numpy
Requires-Dist: matplotlib
